path_link/__init__.py
path_link/builder.py
path_link/cli.py
path_link/get_paths.py
path_link/main.py
path_link/model.py
path_link/project_paths_static.py
path_link/url_factory.py
path_link/url_model.py
path_link/url_static.py
path_link/validation.py
path_link/builtin_validators/__init__.py
path_link/builtin_validators/sandbox.py
path_link/builtin_validators/strict.py
path_link/docs/ai_guidelines.md
path_link/docs/developer_guide.md
path_link/docs/metadata.json
path_link-0.3.1.dist-info/licenses/LICENSE
path_link-0.3.1.dist-info/METADATA
path_link-0.3.1.dist-info/WHEEL
path_link-0.3.1.dist-info/entry_points.txt
path_link-0.3.1.dist-info/top_level.txt
path_link-0.3.1.dist-info/RECORD
