Metadata-Version: 2.4
Name: path-link
Version: 0.3.1
Summary: Type-safe path and URL configuration for Python projects with validation, static models, and IDE autocompletion. Features path management and URL validation with lenient/strict modes.
Author-email: Lasse Tammilehto <lasse@jaahdytyspalvelu.fi>
License-Expression: MIT
Project-URL: Homepage, http://jaahdytyspalvelu.fi
Project-URL: Documentation, https://github.com/jaahdytyspalvelu/path-link#readme
Project-URL: Issue Tracker, https://github.com/jaahdytyspalvelu/path-link/issues
Project-URL: AI Guidelines, https://github.com/jaahdytyspalvelu/path-link/blob/main/assistant_context.md
Project-URL: Developer Guide, https://github.com/jaahdytyspalvelu/path-link/blob/main/CLAUDE.md
Classifier: Development Status :: 4 - Beta
Classifier: Intended Audience :: Developers
Classifier: Programming Language :: Python :: 3
Classifier: Programming Language :: Python :: 3.11
Classifier: Programming Language :: Python :: 3.12
Classifier: Topic :: Software Development :: Libraries :: Python Modules
Classifier: Topic :: Utilities
Classifier: Typing :: Typed
Requires-Python: >=3.11
License-File: LICENSE
Requires-Dist: pydantic>=2.11.0
Requires-Dist: python-dotenv>=1.0.1
Provides-Extra: test
Requires-Dist: pytest>=8.4.2; extra == "test"
Requires-Dist: pytest-cov>=7.0.0; extra == "test"
Provides-Extra: dev
Requires-Dist: mypy>=1.18.2; extra == "dev"
Requires-Dist: ruff>=0.8.0; extra == "dev"
Requires-Dist: twine>=6.2.0; extra == "dev"
Dynamic: license-file
